{
	"info": {
		"_postman_id": "d50dc057-d3ec-4047-be1c-81f36e35d05f",
		"name": "Y9",
		"schema": "https://schema.getpostman.com/json/collection/v2.1.0/collection.json"
	},
	"item": [
		{
			"name": "采购单",
			"request": {
				"method": "GET",
				"header": [],
				"url": {
					"raw": "{{baseUrl}}?cmd=login123",
					"host": [
						"{{baseUrl}}"
					],
					"query": [
						{
							"key": "cmd",
							"value": "login123"
						}
					]
				},
				"description": "http://machine001:11180/PCodeClient/api.ashx?cmd=login123"
			},
			"response": []
		}
	],
	"protocolProfileBehavior": {}
}